bangla_pdf_ocr/__init__.py
bangla_pdf_ocr/ocr.py
bangla_pdf_ocr/data/Freedom Fight.pdf
bangla_pdf_ocr/data/__init__.py
bangla_pdf_ocr/scripts/__init__.py
bangla_pdf_ocr/scripts/install_linux_dependencies.sh
bangla_pdf_ocr/scripts/install_macos_dependencies.sh
bangla_pdf_ocr/scripts/install_windows_dependencies.ps1
bangla_pdf_ocr-0.1.1.dist-info/LICENSE
bangla_pdf_ocr-0.1.1.dist-info/METADATA
bangla_pdf_ocr-0.1.1.dist-info/WHEEL
bangla_pdf_ocr-0.1.1.dist-info/entry_points.txt
bangla_pdf_ocr-0.1.1.dist-info/top_level.txt
bangla_pdf_ocr-0.1.1.dist-info/RECORD
