Metadata-Version: 2.1
Name: bangla-pdf-ocr
Version: 0.1.1
Summary: A package to extract Bengali text from PDFs using OCR
Home-page: https://github.com/asiff00/bangla-pdf-ocr
Author: Abdullah Al Asif
Author-email: asif.dev.bd@gmail.com
Classifier: Programming Language :: Python :: 3
Classifier: License :: OSI Approved :: MIT License
Classifier: Operating System :: OS Independent
Requires-Python: >=3.6
License-File: LICENSE
Requires-Dist: tqdm
Requires-Dist: Pillow
Requires-Dist: pdf2image
Requires-Dist: pytesseract
Requires-Dist: colorama
